shutdown_on_lan/__init__.py
shutdown_on_lan/Arguments.py
shutdown_on_lan/CreateImage.py
shutdown_on_lan/CtkScrollableTextDisabled.py
shutdown_on_lan/Main.py
shutdown_on_lan/Server.py
shutdown_on_lan/Shutdown.py
shutdown_on_lan/Tray.py
shutdown_on_lan-1.0.7.dist-info/entry_points.txt
shutdown_on_lan-1.0.7.dist-info/LICENSE
shutdown_on_lan-1.0.7.dist-info/METADATA
shutdown_on_lan-1.0.7.dist-info/WHEEL
shutdown_on_lan-1.0.7.dist-info/RECORD
