Metadata-Version: 2.1
Name: shutdown-on-lan
Version: 1.0.7
Summary: Shutdown On Lan is a FastAPI application that allows you to remotely shut down the system.
License: GPL-3.0-or-later
Author: Licantropo3392
Author-email: denisalbu287@gmail.com
Requires-Python: >=3.12,<4.0
Classifier: License :: OSI Approved :: GNU General Public License v3 or later (GPLv3+)
Classifier: Programming Language :: Python :: 3
Classifier: Programming Language :: Python :: 3.12
Classifier: Programming Language :: Python :: 3.13
Requires-Dist: customtkinter (>=5.2.2,<6.0.0)
Requires-Dist: fastapi[standard] (>=0.115.6,<0.116.0)
Requires-Dist: pillow (>=11.1.0,<12.0.0)
Requires-Dist: pystray (>=0.19.5,<0.20.0)
